transmisor/probador_TX.v
module tester_TX (
    input [9:0] tx_code_group,
    output reg [7:0] TXD,
    output reg TX_EN,
    output reg TX_ER,
    output reg GTX_CLK,

    input COL,
    output reg mr_main_reset,
    output reg receiving,
    output reg [2:0] xmit
);
    
/* instruccion para crear el reloj
   */
always begin
    GTX_CLK = 1'b0; #1;
    GTX_CLK = 1'b1; #1;
end

initial begin
    TXD = 8'h00;
    TX_EN = 1'b0;
    TX_ER = 1'b0;
    xmit = 3'b001;
    mr_main_reset = 1'b0; #2;

    mr_main_reset = 1'b1;

    #10;
    xmit = 3'b010;
    #10;
    TX_EN = 1'b1;
    #5;
    TXD = 8'h01;
    #2;
    TXD = 8'h02;
    #2;
    TXD = 8'h03;
    #2;
    TXD = 8'h42;
    #2;
    TXD = 8'h50;
    #2;
    TXD = 8'h9A;
    #2;
    TXD = 8'hA6;
    #2;
    TXD = 8'hB5;
    #2;
    TXD = 8'hC5;
    #2;
    TXD = 8'h03;

    #2;
    TXD = 8'h7C;
    #2;
    TXD = 8'hBC;
    #2;
    TXD = 8'hFB;

    #2;
    TX_EN =1'b0;
    #20;
    $finish;
end

endmodule

transmisor/funciones.v
`ifndef FUNCIONES
`define FUNCIONES

`define TRUE  1'b1
`define FALSE 1'b0

`include "Tablas.v"

// PARA DETECTAR EL CODE GROUP
// SI ES COMMA
`define IS_K28_5(RX_CG) ((RX_CG == `K28_5_10b))

`define IS_COMMA(RX_CG) ( \ 
	(RX_CG == `K28_1_10b) || \ 
	(RX_CG == `K28_5_10b) || \ 
	(RX_CG == `K28_7_10b) )

// SI ES DATO VALIDO
`define IS_DATA(RX_CG) ( \ 
	(RX_CG == `D00_0_10b) || \ 
	(RX_CG == `D01_0_10b) || \ 
	(RX_CG == `D02_0_10b) || \ 
	(RX_CG == `D03_0_10b) || \ 
	(RX_CG == `D02_2_10b) || \ 
	(RX_CG == `D16_2_10b) || \ 
	(RX_CG == `D26_4_10b) || \ 
	(RX_CG == `D06_5_10b) || \ 
	(RX_CG == `D21_5_10b) || \ 
	(RX_CG == `D05_6_10b) )

// SI ES CONTROL VALIDO
`define IS_KONTROL(RX_CG) (\ 
	(RX_CG == `K28_0_10b) || \ 
	(RX_CG == `K28_1_10b) || \ 
	(RX_CG == `K28_2_10b) || \ 
	(RX_CG == `K28_3_10b) || \ 
	(RX_CG == `K28_4_10b) || \ 
	(RX_CG == `K28_5_10b) || \ 
	(RX_CG == `K28_6_10b) || \ 
	(RX_CG == `K28_7_10b) || \ 
	(RX_CG == `K23_7_10b) || \ 
	(RX_CG == `K27_7_10b) || \ 
	(RX_CG == `K29_7_10b) || \ 
	(RX_CG == `K30_7_10b) )

// SI ES CONTROL O DATO VALIDO
`define IS_VALID(RX_CG) ((`IS_DATA(RX_CG)) || (`IS_KONTROL(RX_CG)))

`endif

transmisor/Tablas.v
// Codigo muestra Tablas por utilizar

`ifndef TABLAS_CODE_GROUPS
`define TABLAS_CODE_GROUPS

// Tabla de Valid Special Code Groups (Table 36-2), para 8bits

`define K28_0_08b 8'h1C
`define K28_1_08b 8'h3C
`define K28_2_08b 8'h5C
`define K28_3_08b 8'h7C
`define K28_4_08b 8'h9C
// /comma/
`define K28_5_08b 8'hBC  

`define K28_6_08b 8'hDC
`define K28_7_08b 8'hFC

// Carrier_Extend /R/
`define K23_7_08b 8'hF7 

// Start of Packet /S/
`define K27_7_08b 8'hFB 
// End_of_Packet /T/ 
`define K29_7_08b 8'hFD 

// Error_Propagation /V/ 
`define K30_7_08b 8'hFE  


// Tabla de Valid Special Code Groups (Table 36-2), para 10 bits

`define K28_0_10b 10'b11_0000_1011
`define K28_1_10b 10'b11_0000_0110
`define K28_2_10b 10'b11_0000_1010
`define K28_3_10b 10'b11_0000_1100
`define K28_4_10b 10'b11_0000_1101

// /comma/
`define K28_5_10b 10'b11_0000_0101 
`define K28_6_10b 10'b11_0000_1001
`define K28_7_10b 10'b11_0000_0111

// Carrier_Extend /R/
`define K23_7_10b 10'b00_0101_0111  

// Start of Packet /S/
`define K27_7_10b 10'b00_1001_0111  

// End_of_Packet /T/ 
`define K29_7_10b 10'b01_0001_0111  

// Error_Propagation /V/ 
`define K30_7_10b 10'b10_0001_0111  

 
// Tabla de Valid Data Code Groups, para 8 bits

// Table 36-1a
// D0.0
`define D00_0_08b 8'h00
// D1.0
`define D01_0_08b 8'h01
// D2.0
`define D02_0_08b 8'h02
// D3.0
`define D03_0_08b 8'h03

// Table 36-1b
// D2.2
`define D02_2_08b 8'h42
// D16.2
`define D16_2_08b 8'h50

// Table 36-1c
// D26.4
`define D26_4_08b 8'h9A
// D6.5 
`define D06_5_08b 8'hA6

// Table 36-1d
// D21.5
`define D21_5_08b 8'hB5
// D5.6
`define D05_6_08b 8'hC5

//Tabla de Valid Data Code Groups, para 10 bits

// Table 36-1a
// D0.0
`define D00_0_10b 10'b01_1000_1011
// D1.0
`define D01_0_10b 10'b10_0010_1011
// D2.0
`define D02_0_10b 10'b01_0010_1011
// D3.0
`define D03_0_10b 10'b11_0001_0100

// Table 36-1b
// D2.2
`define D02_2_10b 10'b01_0010_0101
// D16.2
`define D16_2_10b 10'b10_0100_0101

// Table 36-1c
// D26.4
`define D26_4_10b 10'b01_0110_0010
// D6.5
`define D06_5_10b 10'b01_1001_1010

// Table 36-1d
// D21.5
`define D21_5_10b 10'b10_1010_1010
// D5.6
`define D05_6_10b 10'b10_1001_0110

`endif

transmisor/macros_TX.v
`ifndef MACROS_TX
`define MACROS_TX

`include "Tablas.v"

`define shift_left(BITS, x) (BITS<<x)
`define UNO_os               `numero_estados_os'h1
`define UNO_cg               `numero_estados_cg'h1
`define UNO_tx_os            `numero_conjuntos_os'h1

//  CODIFICACION DE LOS ESTADOS DE TX ordered set
`define numero_estados_os    8
`define TX_TEST_XMIT        `shift_left(`UNO_os, 0)
`define IDLE                `shift_left(`UNO_os, 1)
`define XMIT_DATA           `shift_left(`UNO_os, 2)
`define START_OF_PACKET     `shift_left(`UNO_os, 3)
`define TX_PACKET           `shift_left(`UNO_os, 4)
`define END_OF_PACKET_NOEXT `shift_left(`UNO_os, 5)
`define EPD2_NOEXT          `shift_left(`UNO_os, 6)
`define EPD3                `shift_left(`UNO_os, 7)

//  CODIFICACION DE LOS ESTADOS DE TX code groups
`define numero_estados_cg    2
`define GENERATE_CODE_GROUPS `shift_left(`UNO_cg, 0)
`define IDLE_I2B             `shift_left(`UNO_cg, 1)

`define numero_conjuntos_os 9

`define tx_os_C             `shift_left(`UNO_tx_os, 0)
`define tx_os_T             `shift_left(`UNO_tx_os, 1)
`define tx_os_R             `shift_left(`UNO_tx_os, 2)
`define tx_os_I             `shift_left(`UNO_tx_os, 3)
`define tx_os_D             `shift_left(`UNO_tx_os, 4)
`define tx_os_S             `shift_left(`UNO_tx_os, 5)
`define tx_os_V             `shift_left(`UNO_tx_os, 6)
`define tx_os_LI            `shift_left(`UNO_tx_os, 7)


module ENCODE (
    input [7:0] valid_cg_8b,
    output reg [9:0] valid_cg_10b
);

always @(valid_cg_8b) begin
    case(valid_cg_8b)
        /*  valid special code groups */
        `K28_0_08b: valid_cg_10b = `K28_0_10b; // K28.0
        `K28_1_08b: valid_cg_10b = `K28_1_10b; // K28.1
        `K28_2_08b: valid_cg_10b = `K28_2_10b; // K28.2
        `K28_3_08b: valid_cg_10b = `K28_3_10b; // K28.3
        `K28_4_08b: valid_cg_10b = `K28_4_10b; // K28.4
        `K28_5_08b: valid_cg_10b = `K28_5_10b; // K28.5
        `K28_6_08b: valid_cg_10b = `K28_6_10b; // K28.6
        `K28_7_08b: valid_cg_10b = `K28_7_10b; // K28.7
        `K23_7_08b: valid_cg_10b = `K23_7_10b; // K23.7 /R/
        `K27_7_08b: valid_cg_10b = `K27_7_10b; // K27.7 /S/
        `K29_7_08b: valid_cg_10b = `K29_7_10b; // K29.7 /T/
        `K30_7_08b: valid_cg_10b = `K30_7_10b; // K30.7 /V/

        /*  valid data code groups */
        `D00_0_08b: valid_cg_10b = `D00_0_10b; // D0.0
        `D01_0_08b: valid_cg_10b = `D01_0_10b; // D1.0
        `D02_0_08b: valid_cg_10b = `D02_0_10b; // D2.0
        `D03_0_08b: valid_cg_10b = `D03_0_10b; // D3.0
        `D02_2_08b: valid_cg_10b = `D02_2_10b; // D2.2
        `D16_2_08b: valid_cg_10b = `D16_2_10b; // D16.2
        `D26_4_08b: valid_cg_10b = `D26_4_10b; // D26.4
        `D06_5_08b: valid_cg_10b = `D06_5_10b; // D6.5
        `D21_5_08b: valid_cg_10b = `D21_5_10b; // D21.5
        `D05_6_08b: valid_cg_10b = `D05_6_10b; // D5.6
    endcase
end
endmodule


module VOID (
    input [`numero_conjuntos_os-1:0] tx_set_in,
    input TX_EN,
    input TX_ER,
    input [7:0] TXD,
    output reg [`numero_conjuntos_os-1:0] tx_set_out
);

always @(*) begin
    if (!TX_EN && TX_ER && TXD[7:0] != 8'h0F)
        tx_set_out = `tx_os_V;
    
    else if (TX_EN && TX_ER) begin
        tx_set_out = `tx_os_V;
    end else
        tx_set_out = tx_set_in;
end

endmodule

module xmit_CHANGE (
    input clk,
    input [2:0] xmit,
    output reg xmitCHANGE
);

    reg [2:0] xmit_old;

    always @(posedge clk ) begin
            xmit_old <= xmit;
    end

    always @(*) begin
        if (xmit == xmit_old)
            xmitCHANGE = `FALSE;

        else
            xmitCHANGE = `TRUE;
    end

endmodule
`endif

transmisor/transmisor_cg.v
`include "funciones.v"
`include "macros_TX.v"

module TRANSMIT_CG (
    input mr_main_reset,
    input GTX_CLK,
    input [6:0] tx_o_set,
    input [7:0] TXD,
    output reg tx_even,
    output reg TX_OSET_indicate,
    output reg [9:0] tx_code_group
);

// función ENCODE(X)
ENCODE data (
    .valid_cg_8b(TXD),
    .valid_cg_10b(TXD_encoded)
);

// variables internas de TX code group
wire [9:0] TXD_encoded;
reg [`numero_estados_cg-1:0] estado_actual;
reg [`numero_estados_cg-1:0] estado_siguiente;


always @(posedge GTX_CLK) begin
    if (!mr_main_reset) begin
        estado_actual <= `GENERATE_CODE_GROUPS;
        TX_OSET_indicate <= `FALSE;
    end else
        estado_actual <= estado_siguiente;
end

always @(*) begin
    // para garantizar el comportamiento del DFF
    estado_siguiente = estado_actual;

    TX_OSET_indicate = `FALSE;
    // implementación de la máquina de estados 
    // de acuerdo al diagrama ASM
    case(estado_actual)
        // GENERATE_CODE_GROUPS
        `GENERATE_CODE_GROUPS: begin
            if (tx_o_set == `tx_os_I) begin
                tx_even = `TRUE;
                tx_code_group = `K28_5_10b; // /K28.5/
                estado_siguiente = `IDLE_I2B;
            end

            else begin
                TX_OSET_indicate = `TRUE;
                tx_even = !tx_even;
                
                if (tx_o_set == `tx_os_R)
                    tx_code_group = `K23_7_10b; // /R/

                if (tx_o_set == `tx_os_S)
                    tx_code_group = `K27_7_10b; // /S/

                if (tx_o_set == `tx_os_T)
                    tx_code_group = `K29_7_10b; // /T/

                if (tx_o_set == `tx_os_V)
                    tx_code_group = `K30_7_10b; // /V/

                if (tx_o_set == `tx_os_D)
                    tx_code_group = TXD_encoded; // ENCODE(TXD)
            end
        end

        // IDLE_I2B
        `IDLE_I2B: begin
            tx_even = `FALSE;
            TX_OSET_indicate = `TRUE;
            tx_code_group = `D16_2_10b; // /D16.2/
            estado_siguiente = `GENERATE_CODE_GROUPS;
        end

        default : estado_siguiente = `GENERATE_CODE_GROUPS;
    endcase

end
endmodule

transmisor/transmisor_os.v
`include "funciones.v"
`include "macros_TX.v"
`include "macros_AN.v"

module TRANSMIT_OS (
    input mr_main_reset,
    input GTX_CLK,
    input [7:0] TXD,
    input TX_EN,
    input TX_ER,
    input receiving,
    input TX_OSET_indicate,
    input tx_even,
    input [2:0] xmit,
    output reg [6:0] tx_o_set,
    output reg COL,
    output reg transmitting,
    output reg [9:0] tx_code_group
);

// función xmitCHANGE
xmit_CHANGE xmit_C (
    .clk(GTX_CLK),
    .xmit(xmit),
    .xmitCHANGE(xmitCHANGE)
);

// función VOID(X)
VOID void (
    .tx_set_in(`tx_os_D),
    .TX_EN(TX_EN),
    .TX_ER(TX_ER),
    .TXD(TXD[7:0]),
    .tx_set_out(tx_set_void)
);

// variables internas de TX ordered set
wire xmitCHANGE;
wire [`numero_conjuntos_os-1:0] tx_set_void;
reg [`numero_estados_os-1:0] estado_actual;
reg [`numero_estados_os-1:0] estado_siguiente;


always @(posedge GTX_CLK) begin
    if (!mr_main_reset || (xmitCHANGE && TX_OSET_indicate && !tx_even)) begin
        estado_actual <= `TX_TEST_XMIT;
        transmitting = `FALSE;
        COL = `FALSE;
    end else
        estado_actual <= estado_siguiente;
end

always @(*) begin

    // para garantizar el comportamiento del DFF
    estado_siguiente = estado_actual;

    // implementación de la máquina de estados
    // de acuerdo al diagrama ASM
    case(estado_actual)
        // TX_TEST_XMIT
        `TX_TEST_XMIT: begin
            transmitting = `FALSE;
            COL = `FALSE;

            if (xmit == `xmit_IDLE || (xmit == `xmit_DATA && (TX_EN || TX_ER)))
                estado_siguiente = `IDLE;
            
            if (xmit == `xmit_DATA && !TX_EN && !TX_ER)
                estado_siguiente = `xmit_DATA;
        end

        // IDLE
        `IDLE: begin
            tx_o_set = `tx_os_I; // /I/

            if (xmit == `xmit_DATA && TX_OSET_indicate && !TX_EN && !TX_ER)
                estado_siguiente = `XMIT_DATA;
        end

        // XMIT_DATA
        `XMIT_DATA: begin
            tx_o_set = `tx_os_I; // /I/

            if (!TX_EN && TX_OSET_indicate)
                estado_siguiente = `XMIT_DATA;
            
            if (TX_EN && !TX_ER && TX_OSET_indicate)
                estado_siguiente = `START_OF_PACKET;
        end

        // START_OF_PACKET
        `START_OF_PACKET: begin
            tx_o_set = `tx_os_S; // /S/
            transmitting = `TRUE;
            COL = receiving;

            if (TX_OSET_indicate)
                estado_siguiente = `TX_PACKET;
        end

        // TX_PACKET
        `TX_PACKET: begin
            if (TX_EN) begin
                tx_o_set = tx_set_void; // VOID(/D/)
                COL = receiving;
            end
            if (!TX_EN && !TX_ER)
                estado_siguiente = `END_OF_PACKET_NOEXT;
        end

        // END_OF_PACKET_NOEXT
        `END_OF_PACKET_NOEXT: begin
            tx_o_set = `tx_os_T; // /T/
            COL = `FALSE;
            if (!tx_even)
                transmitting = `FALSE;

            if (TX_OSET_indicate)
                estado_siguiente = `EPD2_NOEXT;
        end

        // EPD2_NOEXT
        `EPD2_NOEXT: begin
            tx_o_set = `tx_os_R; // /R/
            transmitting = `FALSE;

            if (TX_OSET_indicate) begin
                if (!tx_even)
                    estado_siguiente = `XMIT_DATA;

                else
                    estado_siguiente = `EPD3;
            end
        end

        // EPD3
        `EPD3: begin
            tx_o_set = `tx_os_R; // /R/

            if(TX_OSET_indicate)
                estado_siguiente = `XMIT_DATA;
        end

        default: estado_siguiente = `TX_TEST_XMIT;
    endcase

end

endmodule

transmisor/transmisor.v
`include "transmisor_cg.v"
`include "transmisor_os.v"

module TRANSMIT (
    input mr_main_reset,
    input GTX_CLK,
    input [7:0] TXD,
    input TX_EN,
    input TX_ER,
    input receiving,
    input [2:0] xmit,
    output COL,
    output transmitting,
    output [9:0] tx_code_group
);


// variables internas de TX
wire TX_OSET_indicate;
wire [6:0] tx_o_set;
wire tx_even;

TRANSMIT_OS ordered_set (
    // entradas de TX ordered set
    .mr_main_reset(mr_main_reset),
    .GTX_CLK(GTX_CLK),
    .TXD(TXD[7:0]),
    .TX_EN(TX_EN),
    .TX_ER(TX_ER),
    .tx_even(tx_even),
    .receiving(receiving),
    .TX_OSET_indicate(TX_OSET_indicate),
    .xmit(xmit[2:0]),

    // salidas de TX ordered set
    .tx_o_set(tx_o_set),
    .COL(COL),
    .transmitting(transmitting)
);

TRANSMIT_CG code_group (
    // entradas de TX code group
    .mr_main_reset(mr_main_reset),
    .GTX_CLK(GTX_CLK),
    .tx_o_set(tx_o_set),
    .TXD(TXD[7:0]),

    // salidas de TX code group
    .tx_even(tx_even),
    .TX_OSET_indicate(TX_OSET_indicate),
    .tx_code_group(tx_code_group[9:0])
);

endmodule

transmisor/testbench.v
`include "transmisor.v"
`include "probador_TX.v"

/*  banco de pruebas */
module testbench_TX;
    wire GTX_CLK, TX_EN, TX_ER;
    wire [7:0] TXD, RXD;
    wire [9:0] tx_code_group, rx_code_group;
    wire [2:0] xmit;
    wire COL, transmitting;

    /*  se instancia un DUT */
    TRANSMIT TX (
        .GTX_CLK      (GTX_CLK),
        .mr_main_reset(mr_main_reset),
        .TX_EN        (TX_EN),
        .TX_ER        (TX_ER),
        .receiving    (receiving),
        .xmit         (xmit[2:0]),
        .TXD          (TXD[7:0]),
        .tx_code_group(tx_code_group[9:0]),
        .COL          (COL),
        .transmitting (transmitting)
    );

    /*  se instancia un probador */
    tester_TX probador (
        .GTX_CLK      (GTX_CLK),
        .mr_main_reset(mr_main_reset),
        .TX_EN        (TX_EN),
        .TX_ER        (TX_ER),
        .receiving    (receiving),
        .xmit         (xmit[2:0]),
        .TXD          (TXD[7:0]),
        .tx_code_group(tx_code_group[9:0]),
        .COL(COL)
    );

    /*  para generar las ondas y
        y visualizar en gtkwave
    */
    initial begin
        $dumpfile("resultado.vcd");
        $dumpvars;
    end
endmodule

transmisor/resultado.vcd
$date
	Sun Jun 11 21:43:34 2023
$end
$version
	Icarus Verilog
$end
$timescale
	1s
$end
$scope module testbench_TX $end
$var wire 3 ! xmit [2:0] $end
$var wire 10 " tx_code_group [9:0] $end
$var wire 1 # transmitting $end
$var wire 1 $ receiving $end
$var wire 1 % mr_main_reset $end
$var wire 1 & TX_ER $end
$var wire 1 ' TX_EN $end
$var wire 8 ( TXD [7:0] $end
$var wire 1 ) GTX_CLK $end
$var wire 1 * COL $end
$scope module TX $end
$var wire 3 + xmit [2:0] $end
$var wire 7 , tx_o_set [6:0] $end
$var wire 1 - tx_even $end
$var wire 10 . tx_code_group [9:0] $end
$var wire 1 # transmitting $end
$var wire 1 $ receiving $end
$var wire 1 % mr_main_reset $end
$var wire 1 / TX_OSET_indicate $end
$var wire 1 & TX_ER $end
$var wire 1 ' TX_EN $end
$var wire 8 0 TXD [7:0] $end
$var wire 1 ) GTX_CLK $end
$var wire 1 * COL $end
$scope module code_group $end
$var wire 7 1 tx_o_set [6:0] $end
$var wire 1 % mr_main_reset $end
$var wire 10 2 TXD_encoded [9:0] $end
$var wire 8 3 TXD [7:0] $end
$var wire 1 ) GTX_CLK $end
$var reg 1 / TX_OSET_indicate $end
$var reg 2 4 estado_actual [1:0] $end
$var reg 2 5 estado_siguiente [1:0] $end
$var reg 10 6 tx_code_group [9:0] $end
$var reg 1 - tx_even $end
$scope module data $end
$var wire 8 7 valid_cg_8b [7:0] $end
$var reg 10 8 valid_cg_10b [9:0] $end
$upscope $end
$upscope $end
$scope module ordered_set $end
$var wire 1 / TX_OSET_indicate $end
$var wire 1 - tx_even $end
$var wire 1 9 xmitCHANGE $end
$var wire 3 : xmit [2:0] $end
$var wire 9 ; tx_set_void [8:0] $end
$var wire 1 $ receiving $end
$var wire 1 % mr_main_reset $end
$var wire 1 & TX_ER $end
$var wire 1 ' TX_EN $end
$var wire 8 < TXD [7:0] $end
$var wire 1 ) GTX_CLK $end
$var reg 1 * COL $end
$var reg 8 = estado_actual [7:0] $end
$var reg 8 > estado_siguiente [7:0] $end
$var reg 1 # transmitting $end
$var reg 10 ? tx_code_group [9:0] $end
$var reg 7 @ tx_o_set [6:0] $end
$scope module void $end
$var wire 9 A tx_set_in [8:0] $end
$var wire 1 & TX_ER $end
$var wire 1 ' TX_EN $end
$var wire 8 B TXD [7:0] $end
$var reg 9 C tx_set_out [8:0] $end
$upscope $end
$scope module xmit_C $end
$var wire 3 D xmit [2:0] $end
$var wire 1 ) clk $end
$var reg 1 9 xmitCHANGE $end
$var reg 3 E xmit_old [2:0] $end
$upscope $end
$upscope $end
$upscope $end
$scope module probador $end
$var wire 1 * COL $end
$var wire 10 F tx_code_group [9:0] $end
$var reg 1 ) GTX_CLK $end
$var reg 8 G TXD [7:0] $end
$var reg 1 ' TX_EN $end
$var reg 1 & TX_ER $end
$var reg 1 % mr_main_reset $end
$var reg 1 $ receiving $end
$var reg 3 H xmit [2:0] $end
$upscope $end
$upscope $end
$enddefinitions $end
#0
$dumpvars
b1 H
b0 G
bx F
bx E
b1 D
b10000 C
b0 B
b10000 A
bx @
bx ?
b1 >
bx =
b0 <
b10000 ;
b1 :
19
b110001011 8
b0 7
bx 6
b1 5
bx 4
b0 3
b110001011 2
bx 1
b0 0
0/
bx .
x-
bx ,
b1 +
x*
0)
b0 (
0'
0&
0%
x$
x#
bx "
b1 !
$end
#1
09
b10 >
1/
b1 E
b1 =
b1 4
0*
0#
1)
#2
0)
1%
#3
b10 5
b1100000101 "
b1100000101 .
b1100000101 6
b1100000101 F
1-
0/
b1000 ,
b1000 1
b1000 @
b10 =
1)
#4
0)
#5
b1 5
b1001000101 "
b1001000101 .
b1001000101 6
b1001000101 F
1/
0-
b10 4
1)
#6
0)
#7
b10 5
b1100000101 "
b1100000101 .
b1100000101 6
b1100000101 F
1-
0/
b1 4
1)
#8
0)
#9
b1 5
b1001000101 "
b1001000101 .
b1001000101 6
b1001000101 F
1/
0-
b10 4
1)
#10
0)
#11
b10 5
b1100000101 "
b1100000101 .
b1100000101 6
b1100000101 F
1-
0/
b1 4
1)
#12
19
0)
b10 !
b10 +
b10 :
b10 D
b10 H
#13
b100 >
09
b1 5
b1001000101 "
b1001000101 .
b1001000101 6
b1001000101 F
1/
0-
b10 E
b10 4
1)
#14
0)
#15
b10 5
b1100000101 "
b1100000101 .
b1100000101 6
b1100000101 F
1-
0/
b1 4
b100 =
1)
#16
0)
#17
b1 5
b1001000101 "
b1001000101 .
b1001000101 6
b1001000101 F
1/
0-
b10 4
1)
#18
0)
#19
b10 5
b1100000101 "
b1100000101 .
b1100000101 6
b1100000101 F
1-
0/
b1 4
1)
#20
0)
#21
b1 5
b1001000101 "
b1001000101 .
b1001000101 6
b1001000101 F
1/
0-
b10 4
1)
#22
b1000 >
0)
1'
#23
b10010111 "
b10010111 .
b10010111 6
b10010111 F
1-
1/
b10000 >
x*
1#
b100000 ,
b100000 1
b100000 @
b1 4
b1000 =
1)
#24
0)
#25
b110001011 "
b110001011 .
b110001011 6
b110001011 F
0-
1/
b10000 ,
b10000 1
b10000 @
b10000 =
1)
#26
0)
#27
b1000101011 "
b1000101011 .
b1000101011 6
b1000101011 F
1-
1/
b1000101011 2
b1000101011 8
1)
b1 (
b1 0
b1 3
b1 7
b1 <
b1 B
b1 G
#28
0)
#29
b100101011 "
b100101011 .
b100101011 6
b100101011 F
0-
1/
b100101011 2
b100101011 8
1)
b10 (
b10 0
b10 3
b10 7
b10 <
b10 B
b10 G
#30
0)
#31
b1100010100 "
b1100010100 .
b1100010100 6
b1100010100 F
1-
1/
b1100010100 2
b1100010100 8
1)
b11 (
b11 0
b11 3
b11 7
b11 <
b11 B
b11 G
#32
0)
#33
b100100101 "
b100100101 .
b100100101 6
b100100101 F
0-
1/
b100100101 2
b100100101 8
1)
b1000010 (
b1000010 0
b1000010 3
b1000010 7
b1000010 <
b1000010 B
b1000010 G
#34
0)
#35
b1001000101 "
b1001000101 .
b1001000101 6
b1001000101 F
1-
1/
b1001000101 2
b1001000101 8
1)
b1010000 (
b1010000 0
b1010000 3
b1010000 7
b1010000 <
b1010000 B
b1010000 G
#36
0)
#37
b101100010 "
b101100010 .
b101100010 6
b101100010 F
0-
1/
b101100010 2
b101100010 8
1)
b10011010 (
b10011010 0
b10011010 3
b10011010 7
b10011010 <
b10011010 B
b10011010 G
#38
0)
#39
b110011010 "
b110011010 .
b110011010 6
b110011010 F
1-
1/
b110011010 2
b110011010 8
1)
b10100110 (
b10100110 0
b10100110 3
b10100110 7
b10100110 <
b10100110 B
b10100110 G
#40
0)
#41
b1010101010 "
b1010101010 .
b1010101010 6
b1010101010 F
0-
1/
b1010101010 2
b1010101010 8
1)
b10110101 (
b10110101 0
b10110101 3
b10110101 7
b10110101 <
b10110101 B
b10110101 G
#42
0)
#43
b1010010110 "
b1010010110 .
b1010010110 6
b1010010110 F
1-
1/
b1010010110 2
b1010010110 8
1)
b11000101 (
b11000101 0
b11000101 3
b11000101 7
b11000101 <
b11000101 B
b11000101 G
#44
0)
#45
b1100010100 "
b1100010100 .
b1100010100 6
b1100010100 F
0-
1/
b1100010100 2
b1100010100 8
1)
b11 (
b11 0
b11 3
b11 7
b11 <
b11 B
b11 G
#46
0)
#47
b1100001100 "
b1100001100 .
b1100001100 6
b1100001100 F
1-
1/
b1100001100 2
b1100001100 8
1)
b1111100 (
b1111100 0
b1111100 3
b1111100 7
b1111100 <
b1111100 B
b1111100 G
#48
0)
#49
b1100000101 "
b1100000101 .
b1100000101 6
b1100000101 F
0-
1/
b1100000101 2
b1100000101 8
1)
b10111100 (
b10111100 0
b10111100 3
b10111100 7
b10111100 <
b10111100 B
b10111100 G
#50
0)
#51
b10010111 "
b10010111 .
b10010111 6
b10010111 F
1-
1/
b10010111 2
b10010111 8
1)
b11111011 (
b11111011 0
b11111011 3
b11111011 7
b11111011 <
b11111011 B
b11111011 G
#52
0)
#53
0#
b100010111 "
b100010111 .
b100010111 6
b100010111 F
0-
1/
0*
b10 ,
b10 1
b10 @
b100000 =
b1000000 >
1)
0'
#54
0)
#55
b1010111 "
b1010111 .
b1010111 6
b1010111 F
1-
1/
b10000000 >
b100 ,
b100 1
b100 @
b1000000 =
1)
#56
0)
#57
b100 >
b10000000 =
1)
#58
0)
#59
b10 5
b1100000101 "
b1100000101 .
b1100000101 6
b1100000101 F
0/
b1000 ,
b1000 1
b1000 @
b100 =
1)
#60
0)
#61
b1 5
b1001000101 "
b1001000101 .
b1001000101 6
b1001000101 F
1/
0-
b10 4
1)
#62
0)
#63
b10 5
b1100000101 "
b1100000101 .
b1100000101 6
b1100000101 F
1-
0/
b1 4
1)
#64
0)
#65
b1 5
b1001000101 "
b1001000101 .
b1001000101 6
b1001000101 F
1/
0-
b10 4
1)
#66
0)
#67
b10 5
b1100000101 "
b1100000101 .
b1100000101 6
b1100000101 F
1-
0/
b1 4
1)
#68
0)
#69
b1 5
b1001000101 "
b1001000101 .
b1001000101 6
b1001000101 F
1/
0-
b10 4
1)
#70
0)
#71
b10 5
b1100000101 "
b1100000101 .
b1100000101 6
b1100000101 F
1-
0/
b1 4
1)
#72
0)
#73
b1 5
b1001000101 "
b1001000101 .
b1001000101 6
b1001000101 F
1/
0-
b10 4
1)
